spectrolib/SPECtro.py
spectrolib/__init__.py
spectrolib-0.1.3.dist-info/METADATA
spectrolib-0.1.3.dist-info/WHEEL
spectrolib-0.1.3.dist-info/top_level.txt
spectrolib-0.1.3.dist-info/RECORD
