Metadata-Version: 2.1
Name: spectrolib
Version: 0.1.3
Summary: SPECtro es un paquete que te permite trabajar con mayor facilidad los datos 
Home-page: https://github.com/scoc6656/SPECtro.py
Author: Sigrid Oñate Campos, Ursula Sáez Parra, Irma Pizarro Sáez, Angel Paisano Martinez
Requires-Dist: numpy
Requires-Dist: matplotlib
Requires-Dist: astropy
